<SEC-DOCUMENT>0001127602-16-045096.txt : 20160304
<SEC-HEADER>0001127602-16-045096.hdr.sgml : 20160304
<ACCEPTANCE-DATETIME>20160304164002
ACCESSION NUMBER:		0001127602-16-045096
CONFORMED SUBMISSION TYPE:	4
PUBLIC DOCUMENT COUNT:		1
CONFORMED PERIOD OF REPORT:	20160302
FILED AS OF DATE:		20160304
DATE AS OF CHANGE:		20160304

ISSUER:		

	COMPANY DATA:	
		COMPANY CONFORMED NAME:			Alphabet Inc.
		CENTRAL INDEX KEY:			0001652044
		STANDARD INDUSTRIAL CLASSIFICATION:	SERVICES-COMPUTER PROGRAMMING, DATA PROCESSING, ETC. [7370]
		IRS NUMBER:				611767919
		STATE OF INCORPORATION:			DE
		FISCAL YEAR END:			1231

	BUSINESS ADDRESS:	
		STREET 1:		1600 AMPHITHEATRE PARKWAY
		CITY:			MOUNTAIN VIEW
		STATE:			CA
		ZIP:			94043
		BUSINESS PHONE:		650-253-0000

	MAIL ADDRESS:	
		STREET 1:		1600 AMPHITHEATRE PARKWAY
		CITY:			MOUNTAIN VIEW
		STATE:			CA
		ZIP:			94043

REPORTING-OWNER:	

	OWNER DATA:	
		COMPANY CONFORMED NAME:			Campbell James Grier
		CENTRAL INDEX KEY:			0001667854

	FILING VALUES:
		FORM TYPE:		4
		SEC ACT:		1934 Act
		SEC FILE NUMBER:	001-37580
		FILM NUMBER:		161485743

	MAIL ADDRESS:	
		STREET 1:		1600 AMPHITHEATRE PKWY
		CITY:			MOUNTAIN VIEW
		STATE:			CA
		ZIP:			94043
</SEC-HEADER>
<DOCUMENT>
<TYPE>4
<SEQUENCE>1
<FILENAME>form4.xml
<DESCRIPTION>PRIMARY DOCUMENT
<TEXT>
<XML>
<?xml version="1.0"?>
<ownershipDocument>

    <schemaVersion>X0306</schemaVersion>

    <documentType>4</documentType>

    <periodOfReport>2016-03-02</periodOfReport>

    <issuer>
        <issuerCik>0001652044</issuerCik>
        <issuerName>Alphabet Inc.</issuerName>
        <issuerTradingSymbol>GOOG</issuerTradingSymbol>
    </issuer>

    <reportingOwner>
        <reportingOwnerId>
            <rptOwnerCik>0001667854</rptOwnerCik>
            <rptOwnerName>Campbell James Grier</rptOwnerName>
        </reportingOwnerId>
        <reportingOwnerAddress>
            <rptOwnerStreet1>C/O ALPHABET INC.</rptOwnerStreet1>
            <rptOwnerStreet2>1600 AMPHITHEATRE PRKW.</rptOwnerStreet2>
            <rptOwnerCity>MOUNTAIN VIEW</rptOwnerCity>
            <rptOwnerState>CA</rptOwnerState>
            <rptOwnerZipCode>94043</rptOwnerZipCode>
            <rptOwnerStateDescription></rptOwnerStateDescription>
        </reportingOwnerAddress>
        <reportingOwnerRelationship>
            <isOfficer>1</isOfficer>
            <officerTitle>VP, Alphabet Corp. Controller</officerTitle>
        </reportingOwnerRelationship>
    </reportingOwner>

    <nonDerivativeTable>
        <nonDerivativeTransaction>
            <securityTitle>
                <value>Class C Google Stock Unit</value>
                <footnoteId id="F1"/>
            </securityTitle>
            <transactionDate>
                <value>2016-03-02</value>
            </transactionDate>
            <transactionCoding>
                <transactionFormType>4</transactionFormType>
                <transactionCode>A</transactionCode>
                <equitySwapInvolved>0</equitySwapInvolved>
            </transactionCoding>
            <transactionTimeliness></transactionTimeliness>
            <transactionAmounts>
                <transactionShares>
                    <value>4870</value>
                </transactionShares>
                <transactionPricePerShare>
                    <value>0</value>
                </transactionPricePerShare>
                <transactionAcquiredDisposedCode>
                    <value>A</value>
                </transactionAcquiredDisposedCode>
            </transactionAmounts>
            <postTransactionAmounts>
                <sharesOwnedFollowingTransaction>
                    <value>4870</value>
                </sharesOwnedFollowingTransaction>
            </postTransactionAmounts>
            <ownershipNature>
                <directOrIndirectOwnership>
                    <value>D</value>
                </directOrIndirectOwnership>
            </ownershipNature>
        </nonDerivativeTransaction>
    </nonDerivativeTable>

    <footnotes>
        <footnote id="F1">1/12th of the grant will vest on March 25, 2016, and an additional 1/12th will vest monthly on the 25th day of each month thereafter, subject to the continued employment on such vesting dates.</footnote>
    </footnotes>

    <ownerSignature>
        <signatureName>/s/ Valentina Margulis, as Attorney-in-Fact for James G. Campbell</signatureName>
        <signatureDate>2016-03-04</signatureDate>
    </ownerSignature>
</ownershipDocument>
</XML>
</TEXT>
</DOCUMENT>
</SEC-DOCUMENT>
