<SEC-DOCUMENT>0001127602-16-060111.txt : 20160811
<SEC-HEADER>0001127602-16-060111.hdr.sgml : 20160811
<ACCEPTANCE-DATETIME>20160811174034
ACCESSION NUMBER:		0001127602-16-060111
CONFORMED SUBMISSION TYPE:	4
PUBLIC DOCUMENT COUNT:		1
CONFORMED PERIOD OF REPORT:	20160729
FILED AS OF DATE:		20160811
DATE AS OF CHANGE:		20160811

ISSUER:		

	COMPANY DATA:	
		COMPANY CONFORMED NAME:			FEDEX CORP
		CENTRAL INDEX KEY:			0001048911
		STANDARD INDUSTRIAL CLASSIFICATION:	AIR COURIER SERVICES [4513]
		IRS NUMBER:				621721435
		STATE OF INCORPORATION:			DE
		FISCAL YEAR END:			0531

	BUSINESS ADDRESS:	
		STREET 1:		942 SOUTH SHADY GROVE ROAD
		CITY:			MEMPHIS
		STATE:			TN
		ZIP:			38120-
		BUSINESS PHONE:		9018187500

	MAIL ADDRESS:	
		STREET 1:		942 SOUTH SHADY GROVE ROAD
		CITY:			MEMPHIS
		STATE:			TN
		ZIP:			38120-

	FORMER COMPANY:	
		FORMER CONFORMED NAME:	FDX CORP
		DATE OF NAME CHANGE:	19971103

REPORTING-OWNER:	

	OWNER DATA:	
		COMPANY CONFORMED NAME:			CARTER ROBERT B
		CENTRAL INDEX KEY:			0001197607

	FILING VALUES:
		FORM TYPE:		4
		SEC ACT:		1934 Act
		SEC FILE NUMBER:	001-15829
		FILM NUMBER:		161825611

	MAIL ADDRESS:	
		STREET 1:		942 S SHADY GROVE RD
		CITY:			MEMPHIS
		STATE:			TN
		ZIP:			38120
</SEC-HEADER>
<DOCUMENT>
<TYPE>4
<SEQUENCE>1
<FILENAME>form4.xml
<DESCRIPTION>PRIMARY DOCUMENT
<TEXT>
<XML>
<?xml version="1.0"?>
<ownershipDocument>

    <schemaVersion>X0306</schemaVersion>

    <documentType>4</documentType>

    <periodOfReport>2016-07-29</periodOfReport>

    <issuer>
        <issuerCik>0001048911</issuerCik>
        <issuerName>FEDEX CORP</issuerName>
        <issuerTradingSymbol>FDX</issuerTradingSymbol>
    </issuer>

    <reportingOwner>
        <reportingOwnerId>
            <rptOwnerCik>0001197607</rptOwnerCik>
            <rptOwnerName>CARTER ROBERT B</rptOwnerName>
        </reportingOwnerId>
        <reportingOwnerAddress>
            <rptOwnerStreet1>942 SOUTH SHADY GROVE ROAD</rptOwnerStreet1>
            <rptOwnerStreet2></rptOwnerStreet2>
            <rptOwnerCity>MEMPHIS</rptOwnerCity>
            <rptOwnerState>TN</rptOwnerState>
            <rptOwnerZipCode>38120</rptOwnerZipCode>
            <rptOwnerStateDescription></rptOwnerStateDescription>
        </reportingOwnerAddress>
        <reportingOwnerRelationship>
            <isOfficer>1</isOfficer>
            <officerTitle>EVP Chief Info Officer</officerTitle>
        </reportingOwnerRelationship>
    </reportingOwner>

    <nonDerivativeTable>
        <nonDerivativeTransaction>
            <securityTitle>
                <value>Common Stock</value>
            </securityTitle>
            <transactionDate>
                <value>2016-07-29</value>
            </transactionDate>
            <transactionCoding>
                <transactionFormType>5</transactionFormType>
                <transactionCode>G</transactionCode>
                <equitySwapInvolved>0</equitySwapInvolved>
            </transactionCoding>
            <transactionTimeliness>
                <value>E</value>
            </transactionTimeliness>
            <transactionAmounts>
                <transactionShares>
                    <value>1245</value>
                </transactionShares>
                <transactionPricePerShare>
                    <value>0</value>
                </transactionPricePerShare>
                <transactionAcquiredDisposedCode>
                    <value>D</value>
                </transactionAcquiredDisposedCode>
            </transactionAmounts>
            <postTransactionAmounts>
                <sharesOwnedFollowingTransaction>
                    <value>48399</value>
                </sharesOwnedFollowingTransaction>
            </postTransactionAmounts>
            <ownershipNature>
                <directOrIndirectOwnership>
                    <value>D</value>
                </directOrIndirectOwnership>
            </ownershipNature>
        </nonDerivativeTransaction>
        <nonDerivativeTransaction>
            <securityTitle>
                <value>Common Stock</value>
            </securityTitle>
            <transactionDate>
                <value>2016-07-29</value>
            </transactionDate>
            <transactionCoding>
                <transactionFormType>5</transactionFormType>
                <transactionCode>G</transactionCode>
                <equitySwapInvolved>0</equitySwapInvolved>
            </transactionCoding>
            <transactionTimeliness>
                <value>E</value>
            </transactionTimeliness>
            <transactionAmounts>
                <transactionShares>
                    <value>1245</value>
                </transactionShares>
                <transactionPricePerShare>
                    <value>0</value>
                </transactionPricePerShare>
                <transactionAcquiredDisposedCode>
                    <value>A</value>
                </transactionAcquiredDisposedCode>
            </transactionAmounts>
            <postTransactionAmounts>
                <sharesOwnedFollowingTransaction>
                    <value>1245</value>
                </sharesOwnedFollowingTransaction>
            </postTransactionAmounts>
            <ownershipNature>
                <directOrIndirectOwnership>
                    <value>I</value>
                </directOrIndirectOwnership>
                <natureOfOwnership>
                    <value>By Wife</value>
                </natureOfOwnership>
            </ownershipNature>
        </nonDerivativeTransaction>
    </nonDerivativeTable>

    <footnotes></footnotes>

    <ownerSignature>
        <signatureName>/s/ Robert B. Carter</signatureName>
        <signatureDate>2016-08-11</signatureDate>
    </ownerSignature>
</ownershipDocument>
</XML>
</TEXT>
</DOCUMENT>
</SEC-DOCUMENT>
