<SEC-DOCUMENT>0001209191-15-086695.txt : 20151222
<SEC-HEADER>0001209191-15-086695.hdr.sgml : 20151222
<ACCEPTANCE-DATETIME>20151222174104
ACCESSION NUMBER:		0001209191-15-086695
CONFORMED SUBMISSION TYPE:	4
PUBLIC DOCUMENT COUNT:		1
CONFORMED PERIOD OF REPORT:	20151218
FILED AS OF DATE:		20151222
DATE AS OF CHANGE:		20151222

ISSUER:		

	COMPANY DATA:	
		COMPANY CONFORMED NAME:			SPLUNK INC
		CENTRAL INDEX KEY:			0001353283
		STANDARD INDUSTRIAL CLASSIFICATION:	SERVICES-PREPACKAGED SOFTWARE [7372]
		IRS NUMBER:				861106510
		FISCAL YEAR END:			0131

	BUSINESS ADDRESS:	
		STREET 1:		250 BRANNAN STREET
		CITY:			SAN FRANCISCO
		STATE:			CA
		ZIP:			94107
		BUSINESS PHONE:		415-848-8400

	MAIL ADDRESS:	
		STREET 1:		250 BRANNAN STREET
		CITY:			SAN FRANCISCO
		STATE:			CA
		ZIP:			94107

REPORTING-OWNER:	

	OWNER DATA:	
		COMPANY CONFORMED NAME:			STEIN LEONARD R
		CENTRAL INDEX KEY:			0001226526

	FILING VALUES:
		FORM TYPE:		4
		SEC ACT:		1934 Act
		SEC FILE NUMBER:	001-35498
		FILM NUMBER:		151303750

	MAIL ADDRESS:	
		STREET 1:		SPLUNK INC.
		STREET 2:		250 BRANNAN STREET
		CITY:			SAN FRANCISCO
		STATE:			CA
		ZIP:			94107
</SEC-HEADER>
<DOCUMENT>
<TYPE>4
<SEQUENCE>1
<FILENAME>doc4.xml
<DESCRIPTION>FORM 4 SUBMISSION
<TEXT>
<XML>
<?xml version="1.0"?>
<ownershipDocument>

    <schemaVersion>X0306</schemaVersion>

    <documentType>4</documentType>

    <periodOfReport>2015-12-18</periodOfReport>

    <notSubjectToSection16>0</notSubjectToSection16>

    <issuer>
        <issuerCik>0001353283</issuerCik>
        <issuerName>SPLUNK INC</issuerName>
        <issuerTradingSymbol>SPLK</issuerTradingSymbol>
    </issuer>

    <reportingOwner>
        <reportingOwnerId>
            <rptOwnerCik>0001226526</rptOwnerCik>
            <rptOwnerName>STEIN LEONARD R</rptOwnerName>
        </reportingOwnerId>
        <reportingOwnerAddress>
            <rptOwnerStreet1>C/O SPLUNK INC.</rptOwnerStreet1>
            <rptOwnerStreet2>250 BRANNAN STREET</rptOwnerStreet2>
            <rptOwnerCity>SAN FRANCISCO</rptOwnerCity>
            <rptOwnerState>CA</rptOwnerState>
            <rptOwnerZipCode>94107</rptOwnerZipCode>
            <rptOwnerStateDescription></rptOwnerStateDescription>
        </reportingOwnerAddress>
        <reportingOwnerRelationship>
            <isDirector>0</isDirector>
            <isOfficer>1</isOfficer>
            <isTenPercentOwner>0</isTenPercentOwner>
            <isOther>0</isOther>
            <officerTitle>SVP, General Counsel &amp; Sec.</officerTitle>
        </reportingOwnerRelationship>
    </reportingOwner>

    <nonDerivativeTable>
        <nonDerivativeTransaction>
            <securityTitle>
                <value>Common Stock</value>
            </securityTitle>
            <transactionDate>
                <value>2015-12-14</value>
            </transactionDate>
            <deemedExecutionDate></deemedExecutionDate>
            <transactionCoding>
                <transactionFormType>5</transactionFormType>
                <transactionCode>G</transactionCode>
                <equitySwapInvolved>0</equitySwapInvolved>
            </transactionCoding>
            <transactionTimeliness>
                <value>E</value>
            </transactionTimeliness>
            <transactionAmounts>
                <transactionShares>
                    <value>2100</value>
                </transactionShares>
                <transactionPricePerShare>
                    <value>0.00</value>
                </transactionPricePerShare>
                <transactionAcquiredDisposedCode>
                    <value>D</value>
                </transactionAcquiredDisposedCode>
            </transactionAmounts>
            <postTransactionAmounts>
                <sharesOwnedFollowingTransaction>
                    <value>108211</value>
                </sharesOwnedFollowingTransaction>
            </postTransactionAmounts>
            <ownershipNature>
                <directOrIndirectOwnership>
                    <value>D</value>
                </directOrIndirectOwnership>
            </ownershipNature>
        </nonDerivativeTransaction>
        <nonDerivativeTransaction>
            <securityTitle>
                <value>Common Stock</value>
            </securityTitle>
            <transactionDate>
                <value>2015-12-18</value>
            </transactionDate>
            <deemedExecutionDate></deemedExecutionDate>
            <transactionCoding>
                <transactionFormType>4</transactionFormType>
                <transactionCode>M</transactionCode>
                <equitySwapInvolved>0</equitySwapInvolved>
            </transactionCoding>
            <transactionTimeliness>
                <value></value>
            </transactionTimeliness>
            <transactionAmounts>
                <transactionShares>
                    <value>4167</value>
                </transactionShares>
                <transactionPricePerShare>
                    <value>4.82</value>
                </transactionPricePerShare>
                <transactionAcquiredDisposedCode>
                    <value>A</value>
                </transactionAcquiredDisposedCode>
            </transactionAmounts>
            <postTransactionAmounts>
                <sharesOwnedFollowingTransaction>
                    <value>112383</value>
                    <footnoteId id="F1"/>
                </sharesOwnedFollowingTransaction>
            </postTransactionAmounts>
            <ownershipNature>
                <directOrIndirectOwnership>
                    <value>D</value>
                </directOrIndirectOwnership>
            </ownershipNature>
        </nonDerivativeTransaction>
        <nonDerivativeTransaction>
            <securityTitle>
                <value>Common Stock</value>
            </securityTitle>
            <transactionDate>
                <value>2015-12-18</value>
            </transactionDate>
            <deemedExecutionDate></deemedExecutionDate>
            <transactionCoding>
                <transactionFormType>4</transactionFormType>
                <transactionCode>S</transactionCode>
                <equitySwapInvolved>0</equitySwapInvolved>
                <footnoteId id="F2"/>
            </transactionCoding>
            <transactionTimeliness>
                <value></value>
            </transactionTimeliness>
            <transactionAmounts>
                <transactionShares>
                    <value>6273</value>
                </transactionShares>
                <transactionPricePerShare>
                    <value>53.66</value>
                    <footnoteId id="F3"/>
                </transactionPricePerShare>
                <transactionAcquiredDisposedCode>
                    <value>D</value>
                </transactionAcquiredDisposedCode>
            </transactionAmounts>
            <postTransactionAmounts>
                <sharesOwnedFollowingTransaction>
                    <value>106110</value>
                </sharesOwnedFollowingTransaction>
            </postTransactionAmounts>
            <ownershipNature>
                <directOrIndirectOwnership>
                    <value>D</value>
                </directOrIndirectOwnership>
            </ownershipNature>
        </nonDerivativeTransaction>
        <nonDerivativeTransaction>
            <securityTitle>
                <value>Common Stock</value>
            </securityTitle>
            <transactionDate>
                <value>2015-12-18</value>
            </transactionDate>
            <deemedExecutionDate></deemedExecutionDate>
            <transactionCoding>
                <transactionFormType>4</transactionFormType>
                <transactionCode>S</transactionCode>
                <equitySwapInvolved>0</equitySwapInvolved>
                <footnoteId id="F2"/>
            </transactionCoding>
            <transactionTimeliness>
                <value></value>
            </transactionTimeliness>
            <transactionAmounts>
                <transactionShares>
                    <value>600</value>
                </transactionShares>
                <transactionPricePerShare>
                    <value>54.30</value>
                    <footnoteId id="F4"/>
                </transactionPricePerShare>
                <transactionAcquiredDisposedCode>
                    <value>D</value>
                </transactionAcquiredDisposedCode>
            </transactionAmounts>
            <postTransactionAmounts>
                <sharesOwnedFollowingTransaction>
                    <value>105510</value>
                </sharesOwnedFollowingTransaction>
            </postTransactionAmounts>
            <ownershipNature>
                <directOrIndirectOwnership>
                    <value>D</value>
                </directOrIndirectOwnership>
            </ownershipNature>
        </nonDerivativeTransaction>
    </nonDerivativeTable>

    <derivativeTable>
        <derivativeTransaction>
            <securityTitle>
                <value>Employee Stock Option (right to buy)</value>
            </securityTitle>
            <conversionOrExercisePrice>
                <value>4.82</value>
            </conversionOrExercisePrice>
            <transactionDate>
                <value>2015-12-18</value>
            </transactionDate>
            <deemedExecutionDate></deemedExecutionDate>
            <transactionCoding>
                <transactionFormType>4</transactionFormType>
                <transactionCode>M</transactionCode>
                <equitySwapInvolved>0</equitySwapInvolved>
            </transactionCoding>
            <transactionTimeliness>
                <value></value>
            </transactionTimeliness>
            <transactionAmounts>
                <transactionShares>
                    <value>4167</value>
                </transactionShares>
                <transactionPricePerShare>
                    <value>0.00</value>
                </transactionPricePerShare>
                <transactionAcquiredDisposedCode>
                    <value>D</value>
                </transactionAcquiredDisposedCode>
            </transactionAmounts>
            <exerciseDate>
                <footnoteId id="F5"/>
            </exerciseDate>
            <expirationDate>
                <value>2021-12-14</value>
            </expirationDate>
            <underlyingSecurity>
                <underlyingSecurityTitle>
                    <value>Common Stock</value>
                </underlyingSecurityTitle>
                <underlyingSecurityShares>
                    <value>4167</value>
                </underlyingSecurityShares>
            </underlyingSecurity>
            <postTransactionAmounts>
                <sharesOwnedFollowingTransaction>
                    <value>0</value>
                </sharesOwnedFollowingTransaction>
            </postTransactionAmounts>
            <ownershipNature>
                <directOrIndirectOwnership>
                    <value>D</value>
                </directOrIndirectOwnership>
            </ownershipNature>
        </derivativeTransaction>
    </derivativeTable>

    <footnotes>
        <footnote id="F1">Includes 5 shares acquired under the Splunk Inc. Employee Stock Purchase Plan on December 15, 2015.</footnote>
        <footnote id="F2">The sales reported on this Form 4 were effected pursuant to a Rule 10b5-1 trading plan adopted by the Reporting Person on March 20, 2015.</footnote>
        <footnote id="F3">The price reported in Column 4 is a weighted average price. These shares were sold in multiple transactions at prices ranging from $53.09 to $54.08, inclusive. The Reporting Person undertakes to provide to the Issuer, any security holder of the Issuer, or the staff of the Securities and Exchange Commission, upon request, full information regarding the number of shares sold at each separate price within the ranges set forth in footnotes (3) and (4) to this Form 4.</footnote>
        <footnote id="F4">The price reported in Column 4 is a weighted average price. These shares were sold in multiple transactions at prices ranging from $54.12 to $54.68, inclusive.</footnote>
        <footnote id="F5">The option is fully vested and immediately exercisable.</footnote>
    </footnotes>

    <remarks></remarks>

    <ownerSignature>
        <signatureName>/s/ Steve Dean, by power of attorney</signatureName>
        <signatureDate>2015-12-22</signatureDate>
    </ownerSignature>
</ownershipDocument>
</XML>
</TEXT>
</DOCUMENT>
</SEC-DOCUMENT>
